persistable/__init__.py
persistable/_vineyard.py
persistable/auxiliary.cpython-312-darwin.so
persistable/auxiliary.pyx
persistable/persistable.py
persistable/persistable_interactive.py
persistable/persistence_diagram_h0.cpython-312-darwin.so
persistable/persistence_diagram_h0.pyx
persistable/signed_betti_numbers.cpython-312-darwin.so
persistable/signed_betti_numbers.pyx
persistable/subsampling.cpython-312-darwin.so
persistable/subsampling.pyx
persistable/assets/favicon.ico
persistable/assets/style.css
persistable/borrowed/__init__.py
persistable/borrowed/_hdbscan_boruvka.cpython-312-darwin.so
persistable/borrowed/_hdbscan_boruvka.pxd
persistable/borrowed/_hdbscan_boruvka.pyx
persistable/borrowed/dense_mst.cpython-312-darwin.so
persistable/borrowed/dense_mst.pyx
persistable/borrowed/dist_metrics.cpython-312-darwin.so
persistable/borrowed/dist_metrics.pxd
persistable/borrowed/dist_metrics.pyx
persistable/borrowed/prim_mst.cpython-312-darwin.so
persistable/borrowed/prim_mst.pyx
persistable/test/__init__.py
persistable/test/test_persistable.py
persistable/test/test_ui.py
persistable_clustering-0.5.3.data/data/_hdbscan_boruvka.pxd
persistable_clustering-0.5.3.data/data/dist_metrics.pxd
persistable_clustering-0.5.3.dist-info/LICENSE
persistable_clustering-0.5.3.dist-info/METADATA
persistable_clustering-0.5.3.dist-info/WHEEL
persistable_clustering-0.5.3.dist-info/top_level.txt
persistable_clustering-0.5.3.dist-info/RECORD
