Metadata-Version: 2.1
Name: persistable-clustering
Version: 0.5.3
Summary: Density-based clustering for exploratory data analysis based on multi-parameter persistence
Home-page: https://github.com/LuisScoccola/persistable
Maintainer: Luis Scoccola
Maintainer-email: luis.scoccola@gmail.com
License: 3-clause BSD
Keywords: clustering density hierarchical persistence TDA
Classifier: Development Status :: 4 - Beta
Classifier: Intended Audience :: Science/Research
Classifier: Intended Audience :: Developers
Classifier: License :: OSI Approved
Classifier: Programming Language :: Python
Classifier: Programming Language :: C
Classifier: Topic :: Software Development
Classifier: Topic :: Scientific/Engineering
Classifier: Operating System :: Microsoft :: Windows
Classifier: Operating System :: POSIX
Classifier: Operating System :: Unix
Classifier: Operating System :: MacOS
License-File: LICENSE
Requires-Dist: numpy<2,>=1.21
Requires-Dist: scipy>=1.7
Requires-Dist: scikit-learn>=1.3
Requires-Dist: cython<3,>=0.29
Requires-Dist: plotly>=5.10
Requires-Dist: dash>=2.11
Requires-Dist: diskcache>=5.4
Requires-Dist: multiprocess>=0.70
Requires-Dist: psutil>=5.9
